{
    "DRY_RUN": false,
    "PIPELINE_QUEUE_TO_AME": true,
    "VERBOSE": false,
    "sleepBetweenPhasesMs": 250,
    "ENABLE_FINAL_ALERT": false,
    
    "ENABLE_FILE_LOG": true,
    "PHASE_FILE_LOGS_MASTER_ENABLE": true,
    "DEBUG_DUMP_EFFECTIVE_OPTIONS": false,
    "PHASES_SHARE_PIPELINE_LOG": true,
    "LOG_WITH_TIMESTAMPS": false,
    "PIPELINE_FILE_LOG_APPEND_MODE": false,
    "PIPELINE_FILE_LOG_PRUNE_ENABLED": true,
    "LOG_MAX_FILES": 24,
    "PIPELINE_SHOW_PHASE_TAGS": true,
    "PIPELINE_SHOW_LEVELS": true,
    "LOG_MARKER": "*",

    "RUN_open_project": false,
    "RUN_link_data": true,
    "RUN_save_as_iso": true,
    "RUN_create_compositions": true,
    "RUN_insert_and_relink_footage": true,
    "RUN_add_layers_to_comp": true,
    "RUN_pack_output_comps": true,
    "RUN_set_ame_output_paths": true,
    "RUN_close_project": true,

"batch": {
    "DATA_FS_SUBPATH": ["IN", "data"],
    "FILE_PREFIX": "data_",
    "FILE_SUFFIX": ".json",
    "RUNS_MAX": 0,
    "SLEEP_BETWEEN_RUNS_MS": 500,
    "SAVE_AFTER_RUN": false,
    "DRY_RUN": true
},
"openProject": {
    "PROJECT_TEMPLATE_PATH": "/Users/Jan.Svatuska/Downloads/auto/sau/ronaldo2/POST/WORK/ronaldo2_v05_test.aep",
    "OPEN_IF_DIRTY_BEHAVIOR": "force-no-save"
},
"linkData": {
    "ENABLE_RELINK_DATA_JSON": true,
    "DATA_JSON_ISO_MODE": "manual",
    "DATA_JSON_ISO_CODE_MANUAL": "GBL",
    "DATA_JSON_LANG_CODE_MANUAL": "",
    "DATA_JSON_PROJECT_FOLDER": ["project","in","data"],
    "DATA_JSON_PROJECT_ITEM_NAME": "data.json",
    "DATA_JSON_FS_SUBPATH": ["IN","data"],
    "DATA_JSON_FILE_PREFIX": "data_",
    "DATA_JSON_FILE_SUFFIX": ".json",
    "DATA_JSON_IMPORT_IF_MISSING": true,
    "DATA_JSON_RENAME_IMPORTED_TO_CANONICAL": true,
    "DATA_JSON_LOG_VERBOSE": true
},
"saveAsISO": {
    "OVERWRITE": false,
    "iso": ""
},
"createComps": {
    "ENABLE_FILE_LOG": false,
    "DEFAULT_STILL_DURATION": 5,
    "ENABLE_MARKER_TRIM": false,
    "SKIP_IF_COMP_EXISTS": true,
    "AUTO_FROM_PROJECT_FOOTAGE": true,
    "SKIP_INVALID_DIMENSIONS": false,
    "FOOTAGE_PROJECT_PATH": ["project","in","footage"],
    "FOOTAGE_DATE_YYMMDD": "",
    "INCLUDE_SUBFOLDERS": true,
    "ENABLE_COMP_MOTION_BLUR": true,
    "ENABLE_COMP_FRAME_BLENDING": false,
    "ENABLE_ACCEPT_COMP_SOURCE": true
},
"insertRelink": { 
    "ENABLE_FILE_LOG": false,
    "ENABLE_ALIGN_AUDIO_TO_MARKERS": false,
    "ENABLE_REMOVE_EXISTING_AUDIO_LAYERS": true,
    "ENABLE_MUTE_EXISTING_AUDIO_LAYERS": true,
    "CLEAR_EXISTING_PROJECT_SOUND_FOLDER": true,

    "ENABLE_CHECK_AUDIO_ISO": true,
    "CHECK_AUDIO_ISO_STRICT": false,
    "SOUND_USE_ISO_SUBFOLDER": false,
    "SOUND_FLAT_FALLBACK_TO_ISO_SUBFOLDER": true,
    "SOUND_FLAT_ABORT_IF_NO_ISO_SUBFOLDER": false
    },
"addLayers": {
    "ENABLE_FILE_LOG": true,
    "PIPELINE_SHOW_CONCISE_LOG": true,
    "PIPELINE_SHOW_VERBOSE_LOG": true,
    
    "DEBUG_PARENTING_DUMP": false,
    "DEBUG_PARENTING_DUMP_ONLY_COMPS": [
        "JBL_BensonBoone_TourPro3_06s_9x16", 
        "JBL_BensonBoone_TourPro3_06s_9x16_tiktok"
    ],
    "DEBUG_PARENTING_DUMP_WITH_TRANSFORM": true,
    "DEBUG_PARENTING_COMPARE_TEMPLATE_TARGET": true,

    "PARENTING_ASSIGN_AT_REF_TIME": true,
    "PARENTING_REF_TIME_MODE": "zero",
    "PARENTING_REF_TIME_SECONDS": 0.0,
    
    "SIMPLE_INSERT_TEMPLATE_AS_LAYER": false,
    "SIMPLE_MUTE_TEMPLATE_AUDIO": false,
    "SIMPLE_SOLO_INSERTED_LAYER": false,
    "SIMPLE_PREP_REMOVE_ALL_LAYERS": true,
    "SIMPLE_PREP_DISABLE_FOOTAGE_VIDEO": false,
    "SIMPLE_PREP_MUTE_FOOTAGE_AUDIO": false,

    "ENABLE_AUTOCENTER_ON_AR_MISMATCH": false,
    

    "ENABLE_JSON_TIMING_FOR_DISCLAIMER": false,
    

    "APPLY_INPOINT_TO_LAYER_STARTTIME": true,

    "LAYER_NAME_CONFIG": {
        "info": { 
            "exact": ["info"], 
            "contains": ["info"] 
            },
        "logo": { 
            "exact": ["logo_01", "logo_static", "Size_Holder_Logo"], 
            "contains": [], 
            "imageOnlyForContains": false 
        },
        "logoAnim": { 
            "exact": ["logo_anim", "Size_Holder_Logo"], 
            "contains": [] 
            },
        "logo_02": { 
            "exact": ["logo_02", "Size_Holder_Logo_02"], 
            "contains": [], 
            "imageOnlyForContains": false 
            },
        "logo_03": { 
            "exact": ["logo_03_location_pin"], 
            "contains": ["logo_03"] 
            },
        "logo_04": { 
            "exact": ["logo_04_Formula_1"], 
            "contains": ["logo_04"] 
            },
        "logo_05": { 
            "exact": ["logo_05_F1"], 
            "contains": ["logo_05"] 
            },
        "claim_01": { 
            "exact": ["claim", "Size_Holder_Claim"],
            "contains": [] 
            },
        "claim_02": { 
            "exact": ["claim_02", "Size_Holder_Claim_02"],
            "contains": [] 
            },
        "claim_auxiliary": { 
            "exact": ["web", "__scaler__null__"],
            "contains": [] 
            },
        "disclaimer": { 
            "exact": ["disclaimer", "Size_Holder_Disclaimer"], 
            "contains": [] 
            },
        "disclaimer02": { 
            "exact": ["disclaimer_02"], 
            "contains": [] 
            },
        "subtitles": { 
            "exact": [], 
            "contains": ["subtitles"] 
            },
        "super_A": { 
            "exact": ["super_A", "Size_Holder_Super_A"], 
            "contains": ["super_A"] 
            },
        "dataJson": { 
            "exact": ["DATA_JSON", "data.json"], 
            "contains": [] 
            },
        "recenterRules": { 
            "force": [], 
            "noRecenter": [], 
            "alignH": [], 
            "alignV": [] 
            }
    },
    "TIMING_BEHAVIOR": {
        "logo": "timed",
        "logoAnim": "timed",
        "logo_02": "timed",
        "claim_01": "timed",
        "claim_02": "timed",
        "claim_auxiliary": "timed",

        "logo_03": "span",
        "logo_04": "span",
        "logo_05": "span",
        "disclaimer": "span",
        "disclaimer_02": "span",
        "disclaimer02": "span",
        "subtitles": "span",
        "dataJson": "span",
        "info": "span",
        "template_aspect": "span",
        "center": "span",
        "super_A": "span",
        
        "Size_Holder_Subtitles": "span",
        "DATA_JSON": "span",
        "data.json": "span",
        "Size_Holder_Super_A": "span",
        "Pin": "span"
    },
    "TIMING_ITEM_SELECTOR": {
        "logo": { "mode": "line", "value": 1 },
        "logoAnim": { "mode": "line", "value": 1 },
        "logo_02": { "mode": "line", "value": 2 },
        
        "claim_01": { "mode": "line", "value": 1 },
        "claim_02": { "mode": "line", "value": 2 }
    },
    "SKIP_COPY_CONFIG": { 
        "disclaimerOff":true, 
        "disclaimer02Off": true,
        "subtitlesOff":true, 
        "logoAnimOff":true,
        "logo02Off": true,
        "claim01Off": true,
        "claim02Off": true,
        "groups":{"enabled":false,"keys":[]}, 
        "adHoc":{"enabled":false,"tokens":[]}, 
        "alwaysCopyLogoBaseNames":["Size_Holder_Logo"] 
        },
    "TEMPLATE_MATCH_CONFIG": { 
        "arTolerance": 0.001, 
        "requireAspectRatioMatch": false,
        "enableDurationMatch": true,
        "requireDurationMatch": false,
        "durationToleranceSeconds": 0.5
        },
    "EXTRA_TEMPLATES": {
        "ENABLE_EXTRA_TEMPLATES": true,
        "ALLOWED_AR": ["9x16"],
        "TAG_TOKENS": ["TIKTOK"],
        "OUTPUT_NAME_SUFFIX": "_tiktok",
        
        "REQUIRE_DURATION_MATCH": false,
        "DURATION_TOLERANCE_SECONDS": 0.5
        }
    },
"pack": {
    "PIPELINE_SHOW_CONCISE_LOG": true,
    "PIPELINE_SHOW_VERBOSE_LOG": false,

    "ENABLE_FILE_LOG": false,
    "DRY_RUN_MODE": false,
    "ENABLE_DETAILED_FILE_LOG": false,
    "DEV_VIDEOID_SELF_TEST": false,
    "DEV_VIDEOID_SELF_TEST_USE_SELECTION": false,
    "SUPPRESS_FILE_LOG_WHEN_NOT_DRY_RUN": false,
    "DEBUG_NAMING": false,
    "ENABLE_SUMMARY_LOG": true,
    "USE_PROJECT_LOG_FOLDER": true,
    "PROJECT_LOG_SUBFOLDER": "log",

    "OUTPUT_ROOT_PATH": ["project", "out"],
    "ANCHOR_SOURCE_FOLDER": "comps",
    "APPEND_SUFFIX": "_OUT",
    "ENABLE_SUFFIX_APPEND": false,
    "ENSURE_UNIQUE_NAME": true,
    "SKIP_IF_ALREADY_IN_OUTPUT": true,
    "SKIP_IF_OUTPUT_ALREADY_EXISTS": true,
    "DATA_JSON_PRIMARY_NAME": "data.json"
    },
"ame": {
    "ENABLE_FILE_LOG": false,
    "VERBOSE_DEBUG": false,
    "COMPACT_ITEM_DETAIL": true,
    "PROCESS_SELECTION": true,
    "PROCESS_EXISTING_RQ": true,
    "AUTO_QUEUE_IN_AME": true,
    "AME_MAX_QUEUE_ATTEMPTS": 3,
    "AME_RETRY_DELAY_MS": 650,
    "USE_OM_FILENAME_AS_BASE": false,
    "FILE_LOG_APPEND_MODE": true,
    "USE_LANGUAGE_SUBFOLDER": false,
    "EXPORT_SUBPATH": ["OUT","DELIVERIES"],
    "EXTRA_EXPORT_SUBFOLDER": true,
    "ENABLE_DURATION_SUBFOLDER": true,
    "APPLY_TEMPLATES": false,
    "AUTO_DISABLE_REAPPLY_ON_MISSING": true,
    "DOUBLE_APPLY_OUTPUT_MODULE_TEMPLATES": false,
    "ENABLE_DYNAMIC_OUTPUT_MODULE_SELECTION": true,
    "OUTPUT_MODULE_TEMPLATE": "",
    "OUTPUT_MODULE_TEMPLATE_BY_AR": {
        "1x1": "25Mbs",
        "16x9": "25Mbs",
        "9x16": "25Mbs",
        "4x5": "25Mbs"
        },
    "OUTPUT_MODULE_TEMPLATE_BY_AR_AND_DURATION": {
        "1x1|06s": "Short_1x1",
        "1x1|15s": "Short_1x1_15"
        }
    },
"closeProject": {
    "CLOSE_MODE": "force-save"
    }
}